odoo/addons/ssi_webhook/README.rst
odoo/addons/ssi_webhook/__init__.py
odoo/addons/ssi_webhook/__manifest__.py
odoo/addons/ssi_webhook/menu.xml
odoo/addons/ssi_webhook/auths/__init__.py
odoo/addons/ssi_webhook/auths/api_key.py
odoo/addons/ssi_webhook/auths/basic.py
odoo/addons/ssi_webhook/auths/digest.py
odoo/addons/ssi_webhook/auths/oauth1.py
odoo/addons/ssi_webhook/auths/oauth2.py
odoo/addons/ssi_webhook/controllers/__init__.py
odoo/addons/ssi_webhook/controllers/oauth2_callback.py
odoo/addons/ssi_webhook/data/ir_sequence_data.xml
odoo/addons/ssi_webhook/data/sequence_template_data.xml
odoo/addons/ssi_webhook/models/__init__.py
odoo/addons/ssi_webhook/models/webhook.py
odoo/addons/ssi_webhook/models/webhook_auth.py
odoo/addons/ssi_webhook/models/webhook_history.py
odoo/addons/ssi_webhook/security/ir.model.access.csv
odoo/addons/ssi_webhook/security/ir_module_category_data.xml
odoo/addons/ssi_webhook/security/res_group_data.xml
odoo/addons/ssi_webhook/static/description/icon.png
odoo/addons/ssi_webhook/views/webhook_auth_views.xml
odoo/addons/ssi_webhook/views/webhook_base_views.xml
odoo/addons/ssi_webhook/views/webhook_history.xml
odoo14_addon_ssi_webhook-14.0.1.0.0.dist-info/METADATA
odoo14_addon_ssi_webhook-14.0.1.0.0.dist-info/WHEEL
odoo14_addon_ssi_webhook-14.0.1.0.0.dist-info/top_level.txt
odoo14_addon_ssi_webhook-14.0.1.0.0.dist-info/RECORD
